LICENSE
MANIFEST.in
README.rst
chavo-runner.py
setup.py
app/__init__.py
app/__main__.py
app/chavo.py
app/package_store/.DS_Store
app/package_store/__init__.py
app/package_store/constructor/__init__.py
app/package_store/constructor/constructor.py
app/package_store/oscar/.DS_Store
app/package_store/oscar/__init__.py
app/package_store/oscar/oscar.py
app/package_store/oscar/components/.DS_Store
app/package_store/oscar/components/__init__.py
app/package_store/oscar/components/boot_box.py
app/package_store/oscar/components/boot_nav.py
app/package_store/oscar/components/bootstrap_form.py
app/package_store/oscar/components/box.html
app/package_store/oscar/components/materialize_form.py
app/package_store/oscar/components/portfolio_materialize.py
app/package_store/oscar/components/css_box/__init__.py
app/package_store/oscar/components/css_box/nav.css
app/package_store/oscar/components/html_box/.DS_Store
app/package_store/oscar/components/html_box/__init__.py
app/package_store/oscar/components/html_box/box.html
app/package_store/oscar/components/html_box/nav.html
chavo.egg-info/PKG-INFO
chavo.egg-info/SOURCES.txt
chavo.egg-info/dependency_links.txt
chavo.egg-info/entry_points.txt
chavo.egg-info/top_level.txt