Metadata-Version: 1.0
Name: chavo
Version: 0.1.12
Summary: Command line html creator
Home-page: https://github.com/oscarvazquez/chavo
Author: Oscar Vazquez
Author-email: oscar.vazquez2012@gmail.com
License: UNKNOWN
Platform: UNKNOWN
